odoo/addons/server_env_connector_jira/README.rst
odoo/addons/server_env_connector_jira/__init__.py
odoo/addons/server_env_connector_jira/__manifest__.py
odoo/addons/server_env_connector_jira/i18n/server_env_connector_jira.pot
odoo/addons/server_env_connector_jira/models/__init__.py
odoo/addons/server_env_connector_jira/models/jira_backend.py
odoo/addons/server_env_connector_jira/readme/CONFIGURE.rst
odoo/addons/server_env_connector_jira/readme/CONTRIBUTORS.rst
odoo/addons/server_env_connector_jira/readme/DESCRIPTION.rst
odoo/addons/server_env_connector_jira/static/description/icon.png
odoo/addons/server_env_connector_jira/static/description/index.html
odoo13_addon_server_env_connector_jira-13.0.1.0.1.dist-info/METADATA
odoo13_addon_server_env_connector_jira-13.0.1.0.1.dist-info/WHEEL
odoo13_addon_server_env_connector_jira-13.0.1.0.1.dist-info/top_level.txt
odoo13_addon_server_env_connector_jira-13.0.1.0.1.dist-info/RECORD
